nimbus_haystack/__init__.py
nimbus_haystack/admin.py
nimbus_haystack/apps.py
nimbus_haystack/constants.py
nimbus_haystack/exceptions.py
nimbus_haystack/fields.py
nimbus_haystack/forms.py
nimbus_haystack/generic_views.py
nimbus_haystack/indexes.py
nimbus_haystack/inputs.py
nimbus_haystack/manager.py
nimbus_haystack/models.py
nimbus_haystack/panels.py
nimbus_haystack/query.py
nimbus_haystack/routers.py
nimbus_haystack/signals.py
nimbus_haystack/urls.py
nimbus_haystack/views.py
nimbus_haystack/management/__init__.py
nimbus_haystack/management/commands/__init__.py
nimbus_haystack/management/commands/build_solr_schema.py
nimbus_haystack/management/commands/clear_index.py
nimbus_haystack/management/commands/haystack_info.py
nimbus_haystack/management/commands/rebuild_index.py
nimbus_haystack/management/commands/update_index.py
nimbus_haystack/migrations/__init__.py
nimbus_haystack/templates/panels/haystack.html
nimbus_haystack/templatetags/__init__.py
nimbus_haystack/templatetags/highlight.py
nimbus_haystack/templatetags/more_like_this.py
nimbus_haystack/utils/__init__.py
nimbus_haystack/utils/app_loading.py
nimbus_haystack/utils/geo.py
nimbus_haystack/utils/highlighting.py
nimbus_haystack/utils/loading.py
nimbus_haystack/utils/log.py
nimbus_haystack-0.0.1.dist-info/LICENSE.md
nimbus_haystack-0.0.1.dist-info/METADATA
nimbus_haystack-0.0.1.dist-info/WHEEL
nimbus_haystack-0.0.1.dist-info/top_level.txt
nimbus_haystack-0.0.1.dist-info/RECORD
