Metadata-Version: 2.1
Name: nimbus-haystack
Version: 0.0.1
Summary: nimbus_haystack
Home-page: https://github.com/williamren
Author: william
Author-email: william.ren@live.cn
License: Apache License 2.0
Keywords: nimbus_haystack,nimbus,haystack
Platform: Any
Classifier: Development Status :: 5 - Production/Stable
Classifier: Intended Audience :: Developers
Classifier: License :: OSI Approved :: Apache Software License
Classifier: Operating System :: MacOS :: MacOS X
Classifier: Operating System :: Microsoft :: Windows
Classifier: Operating System :: POSIX
Classifier: Programming Language :: Python
Classifier: Programming Language :: Python :: 2.7
Classifier: Programming Language :: Python :: 3
Classifier: Programming Language :: Python :: 3.3
Classifier: Programming Language :: Python :: 3.4
Classifier: Programming Language :: Python :: 3.5
Classifier: Programming Language :: Python :: 3.6
Classifier: Programming Language :: Python :: 3.7
Requires-Dist: django-haystack (==2.8.1)
Requires-Dist: pysolr (>=3.8.1)
